LICENSE.txt
MANIFEST.in
README.md
setup.cfg
setup.py
insults/__init__.py
insults/classifier.py
insults/core.py
insults/pipeline.py
insults/train.py
insults/util.py
insults.egg-info/PKG-INFO
insults.egg-info/SOURCES.txt
insults.egg-info/dependency_links.txt
insults.egg-info/requires.txt
insults.egg-info/top_level.txt
insults/Logs/__init__.py
insults/data/folds.csv
insults/data/Estimates/estimates.csv
insults/data/Final/README.md
insults/data/Final/final1.csv
insults/data/Final/final10.csv
insults/data/Final/final2.csv
insults/data/Final/final8.csv
insults/data/Final/final9.csv
insults/data/Inputs/final.csv
insults/data/Inputs/fulltrain.csv
insults/data/Inputs/sample_submission_null.csv
insults/data/Inputs/test.csv
insults/data/Inputs/test_with_solutions.csv
insults/data/Inputs/train.csv
insults/data/Submissions/submission1.csv
insults/data/Submissions/submission2.csv
insults/data/Submissions/submission3.csv
insults/models/insult_classifier.joblib.pkl
insults/word_lists/__init__.py
insults/word_lists/google_bad_words.py
insults/word_lists/racist_words.py
insults/word_lists/sexist_words.py
model-exploration/__init__.py