Metadata-Version: 1.1
Name: insults
Version: 0.1.12
Summary: Identify insulting comments and users on social media
Home-page: https://github.com/thundergolfer/Insults
Author: Jonathon Belotti
Author-email: jonathon.bel.melbourne@gmail.com
License: UNKNOWN
Download-URL: https://github.com/thundergolfer/Insult/tarball/0.1
Keywords: machine-learning,social-media,community,data-science
Platform: UNKNOWN
